textwizard/__init__.py
textwizard/text_wizard.py
textwizard/THIRD_PARTY_LICENSES/THIRD-PARTY-DICTIONARIES.md
textwizard/THIRD_PARTY_LICENSES/apache-2.0.txt
textwizard/utils/__init__.py
textwizard/utils/wildcard.py
textwizard/utils/errors/__init__.py
textwizard/utils/errors/errors.py
textwizard/utils/errors/errors_handle.py
textwizard/utils/tw_html_parser/__init__.py
textwizard/utils/tw_html_parser/_utils.py
textwizard/utils/tw_html_parser/beautify_html.py
textwizard/utils/tw_html_parser/dom.py
textwizard/utils/tw_html_parser/entities_hash.c
textwizard/utils/tw_html_parser/entities_hash.h
textwizard/utils/tw_html_parser/entities_wrapper.cp311-win_amd64.pyd
textwizard/utils/tw_html_parser/entities_wrapper.pyx
textwizard/utils/tw_html_parser/error.py
textwizard/utils/tw_html_parser/html_to_md_dom.py
textwizard/utils/tw_html_parser/parser.py
textwizard/utils/tw_html_parser/serializer.py
textwizard/utils/tw_html_parser/serializer_pretty.py
textwizard/utils/tw_html_parser/tokenizer.py
textwizard/utils/tw_html_parser/tokens.py
textwizard/wizard_analyze_text/__init__.py
textwizard/wizard_analyze_text/similarity.py
textwizard/wizard_analyze_text/statistical.py
textwizard/wizard_analyze_text/wizard_correctness/__init__.py
textwizard/wizard_analyze_text/wizard_correctness/_unicode_tokenizer.py
textwizard/wizard_analyze_text/wizard_correctness/_utils.py
textwizard/wizard_analyze_text/wizard_correctness/correctness.py
textwizard/wizard_analyze_text/wizard_correctness/loader_dict.py
textwizard/wizard_analyze_text/wizard_lang_detect/__init__.py
textwizard/wizard_analyze_text/wizard_lang_detect/_utils.py
textwizard/wizard_analyze_text/wizard_lang_detect/detect_lang.py
textwizard/wizard_analyze_text/wizard_lang_detect/gating_scoring.py
textwizard/wizard_analyze_text/wizard_lang_detect/hints.py
textwizard/wizard_analyze_text/wizard_lang_detect/model_io.py
textwizard/wizard_analyze_text/wizard_lang_detect/lang_addons/__init__.py
textwizard-1.1.0.dist-info/licenses/LICENSE
textwizard-1.1.0.dist-info/METADATA
textwizard-1.1.0.dist-info/WHEEL
textwizard-1.1.0.dist-info/top_level.txt
textwizard-1.1.0.dist-info/RECORD
