Metadata-Version: 2.4
Name: textwizard
Version: 1.1.0
Summary: Extract, clean, and analyze text from PDFs, Office docs, images, CSV/HTML. Local OCR (Tesseract), Azure DI, NER (spaCy/Stanza), language detection, spell-check, statistics, and HTML tools.
Author-email: Mattia Rubino <textwizard.dev@gmail.com>
License: TextWizard — Copyright (C) 2024–2025 Mattia Rubino
Project-URL: Homepage, https://github.com/textwizard-dev/textwizard
Project-URL: Source, https://github.com/textwizard-dev/textwizard
Project-URL: Documentation, https://textwizard.readthedocs.io/en/latest/
Keywords: text,ocr,pdf,docx,html,csv,nlp,ner,language-detection,spell-check
Classifier: Programming Language :: Python :: 3
Classifier: Programming Language :: Python :: 3.9
Classifier: Programming Language :: Python :: 3.10
Classifier: Programming Language :: Python :: 3.11
Classifier: Intended Audience :: Developers
Classifier: Topic :: Text Processing
Classifier: License :: OSI Approved :: GNU Affero General Public License v3 or later (AGPLv3+)
Requires-Python: >=3.9
License-File: LICENSE
Requires-Dist: pandas>=2.3.1
Requires-Dist: PyMuPDF>=1.25.0
Requires-Dist: pytesseract>=0.3.13
Requires-Dist: xlrd>=2.0.1
Requires-Dist: openpyxl>=3.1.5
Requires-Dist: marisa-trie>=1.3.0
Requires-Dist: zstandard>=0.22
Requires-Dist: platformdirs>=4.0
Requires-Dist: regex>=2024.11.6
Requires-Dist: pyahocorasick>=2.2.0
Requires-Dist: lxml>=5.0.0
Provides-Extra: azure
Requires-Dist: azure-ai-documentintelligence>=1.0.2; extra == "azure"
Requires-Dist: azure-core>=1.24.0; extra == "azure"
Provides-Extra: ner
Requires-Dist: spacy>=3.5.0; extra == "ner"
Requires-Dist: stanza>=1.5.0; extra == "ner"
Requires-Dist: spacy-stanza>=0.3.0; extra == "ner"
Provides-Extra: all
Requires-Dist: azure-ai-documentintelligence>=1.0.2; extra == "all"
Requires-Dist: azure-core>=1.24.0; extra == "all"
Requires-Dist: spacy>=3.5.0; extra == "all"
Requires-Dist: stanza>=1.5.0; extra == "all"
Requires-Dist: spacy-stanza>=0.3.0; extra == "all"
Dynamic: license-file
